{
	"configurations" : 
	[
		{
			"directories" : 
			[
				{
					"build" : ".",
					"childIndexes" : 
					[
						1,
						2
					],
					"jsonFile" : "directory-.-Debug-f5ebdc15457944623624.json",
					"minimumCMakeVersion" : 
					{
						"string" : "3.27"
					},
					"projectIndex" : 0,
					"source" : "."
				},
				{
					"build" : "logic",
					"jsonFile" : "directory-logic-Debug-eb2f19c2b30e1f6a8eed.json",
					"minimumCMakeVersion" : 
					{
						"string" : "3.27"
					},
					"parentIndex" : 0,
					"projectIndex" : 0,
					"source" : "logic",
					"targetIndexes" : 
					[
						1
					]
				},
				{
					"build" : "view",
					"jsonFile" : "directory-view-Debug-e6a29e2082744aa1ddf4.json",
					"minimumCMakeVersion" : 
					{
						"string" : "3.27"
					},
					"parentIndex" : 0,
					"projectIndex" : 0,
					"source" : "view",
					"targetIndexes" : 
					[
						0
					]
				}
			],
			"name" : "Debug",
			"projects" : 
			[
				{
					"directoryIndexes" : 
					[
						0,
						1,
						2
					],
					"name" : "Doodle",
					"targetIndexes" : 
					[
						0,
						1
					]
				}
			],
			"targets" : 
			[
				{
					"directoryIndex" : 2,
					"id" : "Doodle::@4e967fb687f3edd34c3f",
					"jsonFile" : "target-Doodle-Debug-bd14c1714ab8e4145163.json",
					"name" : "Doodle",
					"projectIndex" : 0
				},
				{
					"directoryIndex" : 1,
					"id" : "logic::@330d13901b3cda70f4f4",
					"jsonFile" : "target-logic-Debug-7c3caed049dfcff23e06.json",
					"name" : "logic",
					"projectIndex" : 0
				}
			]
		}
	],
	"kind" : "codemodel",
	"paths" : 
	{
		"build" : "/Users/camilledevuyst/CLionProjects/Doodle/cmake-build-debug",
		"source" : "/Users/camilledevuyst/CLionProjects/Doodle"
	},
	"version" : 
	{
		"major" : 2,
		"minor" : 7
	}
}
